<JavaCardProject name="XemPhimTichDiem">
<USER>
<PKG name="auth" aid="11 22 33 44 55 88 00 00" major="1" minor="0">
<APPLET aid="11 22 33 44 55 88 00" instanceaid="" parameter="" authority="" privileges="" index="27744" name="pin"/>
<APPLET aid="11 22 33 44 55 88 01" instanceaid="" parameter="" authority="" privileges="" index="-17664" name="information"/>
<APPLET aid="11 22 33 44 55 88 02" instanceaid="" parameter="" authority="" privileges="" index="-26152" name="cinema"/>
</PKG>
<Libs/>
</USER>
<DebugInfo>
<Protocol name="T1"/>
</DebugInfo>
</JavaCardProject>
